afwf/__init__.py
afwf/_icon.py
afwf/_version.py
afwf/api.py
afwf/handler.py
afwf/icon.py
afwf/item.py
afwf/paths.py
afwf/query.py
afwf/script_filter.py
afwf/script_filter_object.py
afwf/workflow.py
afwf/__pycache__/__init__.cpython-38.pyc
afwf/__pycache__/_icon.cpython-38.pyc
afwf/__pycache__/_version.cpython-38.pyc
afwf/__pycache__/api.cpython-38.pyc
afwf/__pycache__/handler.cpython-38.pyc
afwf/__pycache__/icon.cpython-38.pyc
afwf/__pycache__/item.cpython-38.pyc
afwf/__pycache__/paths.cpython-38.pyc
afwf/__pycache__/query.cpython-38.pyc
afwf/__pycache__/script_filter.cpython-38.pyc
afwf/__pycache__/script_filter_object.cpython-38.pyc
afwf/__pycache__/workflow.cpython-38.pyc
afwf/docs/__init__.py
afwf/docs/__pycache__/__init__.cpython-38.pyc
afwf/example_wf/__init__.py
afwf/example_wf/cache.py
afwf/example_wf/__pycache__/__init__.cpython-38.pyc
afwf/example_wf/__pycache__/cache.cpython-38.pyc
afwf/example_wf/handlers/__init__.py
afwf/example_wf/handlers/python_version.py
afwf/example_wf/handlers/__pycache__/__init__.cpython-38.pyc
afwf/example_wf/handlers/__pycache__/python_version.cpython-38.pyc
afwf/icons/android-96.png
afwf/icons/archive-folder-96.png
afwf/icons/bash-96.png
afwf/icons/bookmark-96.png
afwf/icons/box-96.png
afwf/icons/calendar-96.png
afwf/icons/chat-96.png
afwf/icons/check-96.png
afwf/icons/close-96.png
afwf/icons/code-96.png
afwf/icons/console-96.png
afwf/icons/debug-96.png
afwf/icons/desktop-96.png
afwf/icons/dictionary-96.png
afwf/icons/download-96.png
afwf/icons/error-96.png
afwf/icons/explosion-96.png
afwf/icons/file-96.png
afwf/icons/fire-96.png
afwf/icons/flask-96.png
afwf/icons/folder-96.png
afwf/icons/gear-96.png
afwf/icons/git-96.png
afwf/icons/groupchat-96.png
afwf/icons/id-card-96.png
afwf/icons/idea-96.png
afwf/icons/info-96.png
afwf/icons/internet-96.png
afwf/icons/iphone-96.png
afwf/icons/landline-96.png
afwf/icons/laptop-96.png
afwf/icons/mail-96.png
afwf/icons/meeting-96.png
afwf/icons/message-96.png
afwf-0.6.1.dist-info/AUTHORS.rst
afwf-0.6.1.dist-info/LICENSE.txt
afwf-0.6.1.dist-info/METADATA
afwf-0.6.1.dist-info/WHEEL
afwf-0.6.1.dist-info/top_level.txt
afwf-0.6.1.dist-info/RECORD
