Metadata-Version: 2.1
Name: afwf
Version: 0.6.1
Summary: A powerful framework enables fast and elegant development of Alfred Workflows in Python.
Home-page: https://github.com/MacHu-GWU/afwf-project
Download-URL: https://pypi.python.org/pypi/afwf/0.6.1#downloads
Author: Sanhe Hu
Author-email: husanhe@gmail.com
Maintainer: Sanhe Hu
Maintainer-email: husanhe@gmail.com
License: MIT
Platform: Windows
Platform: MacOS
Platform: Unix
Classifier: Development Status :: 4 - Beta
Classifier: Intended Audience :: Developers
Classifier: License :: OSI Approved :: MIT License
Classifier: Natural Language :: English
Classifier: Operating System :: Microsoft :: Windows
Classifier: Operating System :: MacOS
Classifier: Operating System :: Unix
Classifier: Programming Language :: Python
Classifier: Programming Language :: Python :: 3 :: Only
Classifier: Programming Language :: Python :: 3.7
Classifier: Programming Language :: Python :: 3.8
Classifier: Programming Language :: Python :: 3.9
Classifier: Programming Language :: Python :: 3.10
Classifier: Programming Language :: Python :: 3.11
Classifier: Programming Language :: Python :: 3.12
Requires-Python: >=3.7
License-File: LICENSE.txt
License-File: AUTHORS.rst
Requires-Dist: attrs >=21.3.0
Requires-Dist: attrs-mate <2.0.0,>=1.1.1
Provides-Extra: docs
Requires-Dist: Sphinx ==5.3.0 ; extra == 'docs'
Requires-Dist: sphinx-jinja ==2.0.2 ; extra == 'docs'
Requires-Dist: sphinx-copybutton ==0.5.1 ; extra == 'docs'
Requires-Dist: sphinx-design ==0.5.0 ; extra == 'docs'
Requires-Dist: furo ==2023.03.27 ; extra == 'docs'
Requires-Dist: nbsphinx ==0.8.12 ; extra == 'docs'
Requires-Dist: rstobj ==1.2.1 ; extra == 'docs'
Requires-Dist: pygments ==2.15.1 ; extra == 'docs'
Requires-Dist: ipython ==8.10.0 ; extra == 'docs'
Requires-Dist: docfly ==2.0.1 ; extra == 'docs'
Provides-Extra: tests
Requires-Dist: pytest ; extra == 'tests'
Requires-Dist: pytest-cov ; extra == 'tests'
Requires-Dist: requests <3.0.0,>=2.26.0 ; extra == 'tests'
Requires-Dist: beautifulsoup4 <5.0.0,>=4.10.0 ; extra == 'tests'
Requires-Dist: pathlib-mate <2.0.0,>=1.3.1 ; extra == 'tests'
Requires-Dist: diskcache <6.0.0,>=5.4.0 ; extra == 'tests'
Requires-Dist: fuzzywuzzy <1.0.0,>=0.18.0 ; extra == 'tests'
Requires-Dist: rich ; extra == 'tests'
